xklb/__init__.py
xklb/__main__.py
xklb/lb.py
xklb/readme.py
xklb/usage.py
xklb/assets/__init__.py
xklb/assets/calibre.css
xklb/createdb/__init__.py
xklb/createdb/av.py
xklb/createdb/computer_info.py
xklb/createdb/computers_add.py
xklb/createdb/fs_add.py
xklb/createdb/fs_add_metadata.py
xklb/createdb/gallery_add.py
xklb/createdb/gallery_backend.py
xklb/createdb/hn_add.py
xklb/createdb/links_add.py
xklb/createdb/nicotine_import.py
xklb/createdb/places_import.py
xklb/createdb/reddit_add.py
xklb/createdb/row_add.py
xklb/createdb/site_add.py
xklb/createdb/substack.py
xklb/createdb/subtitle.py
xklb/createdb/tables_add.py
xklb/createdb/tabs_add.py
xklb/createdb/tildes.py
xklb/createdb/torrents_add.py
xklb/createdb/tube_add.py
xklb/createdb/tube_backend.py
xklb/createdb/web_add.py
xklb/data/__init__.py
xklb/data/dictionary.pkl
xklb/data/ffmpeg_errors.py
xklb/data/http_errors.py
xklb/data/imagemagick_errors.py
xklb/data/unar_errors.py
xklb/data/wordbank.py
xklb/data/yt_dlp_errors.py
xklb/editdb/__init__.py
xklb/editdb/dedupe_db.py
xklb/editdb/dedupe_media.py
xklb/editdb/merge_online_local.py
xklb/editdb/mpv_watchlater.py
xklb/editdb/pushshift.py
xklb/editdb/reddit_selftext.py
xklb/files/__init__.py
xklb/files/christen.py
xklb/files/llm_map.py
xklb/files/sample_compare.py
xklb/files/sample_hash.py
xklb/files/similar_files.py
xklb/folders/__init__.py
xklb/folders/big_dirs.py
xklb/folders/merge_folders.py
xklb/folders/merge_mv.py
xklb/folders/mergerfs_cp.py
xklb/folders/mount_stats.py
xklb/folders/move_list.py
xklb/folders/scatter.py
xklb/folders/similar_folders.py
xklb/fsdb/__init__.py
xklb/fsdb/disk_usage.py
xklb/fsdb/search_db.py
xklb/mediadb/__init__.py
xklb/mediadb/block.py
xklb/mediadb/db_history.py
xklb/mediadb/db_media.py
xklb/mediadb/db_playlists.py
xklb/mediadb/download.py
xklb/mediadb/download_status.py
xklb/mediadb/history.py
xklb/mediadb/history_add.py
xklb/mediadb/optimize_db.py
xklb/mediadb/playlists.py
xklb/mediadb/redownload.py
xklb/mediadb/search.py
xklb-3.0.33.dist-info/METADATA
xklb-3.0.33.dist-info/WHEEL
xklb-3.0.33.dist-info/entry_points.txt
xklb-3.0.33.dist-info/licenses/LICENSE
xklb-3.0.33.dist-info/RECORD
