Metadata-Version: 2.3
Name: xklb
Version: 3.0.33
Summary: xk library
Project-URL: documentation, https://github.com/chapmanjacobd/library#usage
Project-URL: homepage, https://github.com/chapmanjacobd/library#readme
Project-URL: repository, https://github.com/chapmanjacobd/library/
Author-email: Jacob Chapman <7908073+chapmanjacobd@users.noreply.github.com>
License: BSD 3-Clause License
Requires-Python: >=3.11
Requires-Dist: beautifulsoup4>=4.10.0
Requires-Dist: ffmpeg-python
Requires-Dist: ftfy
Requires-Dist: gallery-dl
Requires-Dist: humanize
Requires-Dist: ipython
Requires-Dist: lxml
Requires-Dist: markdown
Requires-Dist: mutagen
Requires-Dist: natsort
Requires-Dist: praw
Requires-Dist: puremagic
Requires-Dist: pysubs2
Requires-Dist: python-dateutil
Requires-Dist: python-mpv-jsonipc
Requires-Dist: regex
Requires-Dist: rich
Requires-Dist: screeninfo
Requires-Dist: sqlite-utils
Requires-Dist: tabulate
Requires-Dist: tinytag
Requires-Dist: yt-dlp[default]
Provides-Extra: deluxe
Requires-Dist: aiohttp; extra == 'deluxe'
Requires-Dist: annoy; extra == 'deluxe'
Requires-Dist: catt; extra == 'deluxe'
Requires-Dist: geopandas; extra == 'deluxe'
Requires-Dist: img2pdf; extra == 'deluxe'
Requires-Dist: ocrmypdf; extra == 'deluxe'
Requires-Dist: openpyxl; extra == 'deluxe'
Requires-Dist: paramiko; extra == 'deluxe'
Requires-Dist: pdf2image; extra == 'deluxe'
Requires-Dist: pillow; extra == 'deluxe'
Requires-Dist: pyexiftool; extra == 'deluxe'
Requires-Dist: pymcdm; extra == 'deluxe'
Requires-Dist: pyvirtualdisplay; extra == 'deluxe'
Requires-Dist: qbittorrent-api; extra == 'deluxe'
Requires-Dist: scikit-learn; extra == 'deluxe'
Requires-Dist: selenium-wire; extra == 'deluxe'
Requires-Dist: subliminal; extra == 'deluxe'
Requires-Dist: torrentool; extra == 'deluxe'
Requires-Dist: tqdm; extra == 'deluxe'
Requires-Dist: wordllama>=0.2.7.post0; extra == 'deluxe'
Requires-Dist: xattr; extra == 'deluxe'
Provides-Extra: dev
Requires-Dist: black; extra == 'dev'
Requires-Dist: isort; extra == 'dev'
Requires-Dist: ssort; extra == 'dev'
Provides-Extra: fat
Requires-Dist: brotab; extra == 'fat'
Requires-Dist: ghostscript; extra == 'fat'
Requires-Dist: opencv-python; extra == 'fat'
Requires-Dist: orjson; extra == 'fat'
Requires-Dist: pypdf-table-extraction; extra == 'fat'
Requires-Dist: textract-py3==2.0.1; extra == 'fat'
Provides-Extra: test
Requires-Dist: freezegun; extra == 'test'
Requires-Dist: pandas; extra == 'test'
Requires-Dist: pyfakefs; extra == 'test'
Requires-Dist: pytest; extra == 'test'
Requires-Dist: pytest-regressions; extra == 'test'
Requires-Dist: ruff; extra == 'test'
